mesos_provider/__init__.py
airflow_provider_mesos-0.1.2.dist-info/METADATA
airflow_provider_mesos-0.1.2.dist-info/WHEEL
airflow_provider_mesos-0.1.2.dist-info/top_level.txt
airflow_provider_mesos-0.1.2.dist-info/RECORD
