Metadata-Version: 2.1
Name: airflow-provider-mesos
Version: 0.1.2
Summary: Apache Mesos Provider
Home-page: https://www.aventer.biz/
Author: Andreas Peters
Author-email: support@aventer.biz
License: Apache License 2.0
Platform: UNKNOWN
Requires-Python: ~=3.8
Requires-Dist: apache-airflow (>=2.0)
